README
setup.py
src/Preferences/__init__.py
src/Preferences/tests.py
src/Preferences.egg-info/PKG-INFO
src/Preferences.egg-info/SOURCES.txt
src/Preferences.egg-info/dependency_links.txt
src/Preferences.egg-info/requires.txt
src/Preferences.egg-info/top_level.txt