Metadata-Version: 1.0
Name: Preferences
Version: 0.08
Summary: It a simple class that creates a list of dictionarries to store preferences as key value pairs.  You can use the class directly or load  the preferences from files.  The main reason I wrote it was to create an easy way of storing more than one preference with the same name and load them form files in a manner that allows for easy appending or replacing of parmeters that could have been loaded from a default prameter file.  There are also several methods to make  managing the preferences
Home-page: http://preferences.django-development.com/
Author: Mark Anderson
Author-email: nosrednakram@gmail.com
License: BSD
Platform: UNKNOWN
Classifier: Development Status :: 3 - Alpha
Classifier: Operating System :: OS Independent
Classifier: Intended Audience :: Developers
Classifier: License :: OSI Approved :: BSD License
Classifier: Programming Language :: Python
Classifier: Topic :: Utilities
